dowg/CoordinateDoWG.py
dowg/ScalarDoWG.py
dowg/__init__.py
dowg/clip.py
dowg-0.3.1.dist-info/LICENSE
dowg-0.3.1.dist-info/METADATA
dowg-0.3.1.dist-info/WHEEL
dowg-0.3.1.dist-info/top_level.txt
dowg-0.3.1.dist-info/RECORD
