Metadata-Version: 2.1
Name: dowg
Version: 0.3.1
Summary: DoWG parameter-free adaptive optimizer
Author-email: Patrick Shanahan <patrick.e.shanahan@gmail.com>
Project-URL: Homepage, https://github.com/AMorporkian/dowg
Classifier: Programming Language :: Python :: 3
Classifier: License :: OSI Approved :: MIT License
Classifier: Operating System :: OS Independent
Requires-Python: >=3.7
License-File: LICENSE
